pyairports/__init__.py
pyairports/airports.py
pyairports/data/airport_list.json
pyairports/data/other_list.json
pyairports-2.1.1.dist-info/LICENSE.txt
pyairports-2.1.1.dist-info/METADATA
pyairports-2.1.1.dist-info/WHEEL
pyairports-2.1.1.dist-info/entry_points.txt
pyairports-2.1.1.dist-info/top_level.txt
pyairports-2.1.1.dist-info/RECORD
