Metadata-Version: 2.1
Name: pyairports
Version: 2.1.1
Summary: Airport and other locations database
Home-page: https://github.com/ozeliger/pyairports
Author: Jason Dsouza
License: Apache Software License
Keywords: Airports
Platform: UNKNOWN
Classifier: Development Status :: 5 - Production/Stable
Classifier: Intended Audience :: Developers
Classifier: License :: OSI Approved :: Apache Software License
Classifier: Programming Language :: Python :: 3
Classifier: Programming Language :: Python :: 3 :: Only
Classifier: Programming Language :: Python :: 3.6
Classifier: Programming Language :: Python :: 3.7
Classifier: Programming Language :: Python :: 3.8
License-File: LICENSE.txt
